matrix_cloud/__about__.py
matrix_cloud/__init__.py
matrix_cloud/__main__.py
matrix_cloud/gui.py
matrix_cloud/py.typed
matrix_cloud-0.0.3.dist-info/METADATA
matrix_cloud-0.0.3.dist-info/WHEEL
matrix_cloud-0.0.3.dist-info/licenses/LICENSE.txt
matrix_cloud-0.0.3.dist-info/RECORD
